oarepo_doi_resolver/__init__.py
oarepo_doi_resolver/ext.py
oarepo_doi_resolver/relatedItems_metadata_mapping.py
oarepo_doi_resolver/version.py
oarepo_doi_resolver-1.1.1.dist-info/LICENSE
oarepo_doi_resolver-1.1.1.dist-info/METADATA
oarepo_doi_resolver-1.1.1.dist-info/WHEEL
oarepo_doi_resolver-1.1.1.dist-info/entry_points.txt
oarepo_doi_resolver-1.1.1.dist-info/top_level.txt
oarepo_doi_resolver-1.1.1.dist-info/RECORD
