Metadata-Version: 2.1
Name: oarepo-doi-resolver
Version: 1.1.1
Summary: DOI resolver for OARepo
Home-page: https://github.com/oarepo/oarepo-dc
Author: Alzbeta Pokorna
Author-email: alzbeta.pokorna@cesnet.cz
License: MIT
Platform: any
Classifier: Environment :: Web Environment
Classifier: Intended Audience :: Developers
Classifier: License :: OSI Approved :: MIT License
Classifier: Operating System :: OS Independent
Classifier: Programming Language :: Python
Classifier: Topic :: Internet :: WWW/HTTP :: Dynamic Content
Classifier: Topic :: Software Development :: Libraries :: Python Modules
Classifier: Programming Language :: Python :: 2
Classifier: Programming Language :: Python :: 2.7
Classifier: Programming Language :: Python :: 3
Classifier: Programming Language :: Python :: 3.5
Classifier: Development Status :: 4 - Beta
License-File: LICENSE
Requires-Dist: crossrefapi
Requires-Dist: langdetect
Requires-Dist: deepmerge
Provides-Extra: build
Requires-Dist: oarepo-model-builder ; extra == 'build'
Provides-Extra: tests
Requires-Dist: oarepo-validate ; extra == 'tests'
Requires-Dist: crossrefapi ; extra == 'tests'
Requires-Dist: deepmerge ; extra == 'tests'
Requires-Dist: oarepo[tests] ; extra == 'tests'
